arcaptcha/Arcaptcha.py
arcaptcha/__init__.py
arcaptcha-1.0.0.dist-info/METADATA
arcaptcha-1.0.0.dist-info/WHEEL
arcaptcha-1.0.0.dist-info/top_level.txt
arcaptcha-1.0.0.dist-info/RECORD
