Metadata-Version: 2.1
Name: arcaptcha
Version: 1.0.0
Summary: Python package for Arcaptcha
Home-page: UNKNOWN
Author: EVOKE
Author-email: evoke.lektrique@gmail.com
License: UNKNOWN
Keywords: captcha,api
Platform: UNKNOWN
Requires-Dist: requests
